yunbk/__init__.py
yunbk/constants.py
yunbk/log.py
yunbk/six.py
yunbk/utils.py
yunbk/yunbk.py
yunbk/backend/__init__.py
yunbk/backend/ali_oss.py
yunbk/backend/base.py
yunbk/backend/ftp.py
yunbk/backend/local.py
yunbk/backend/sftp.py
yunbk-0.2.3.dist-info/LICENSE
yunbk-0.2.3.dist-info/METADATA
yunbk-0.2.3.dist-info/WHEEL
yunbk-0.2.3.dist-info/top_level.txt
yunbk-0.2.3.dist-info/RECORD
