Metadata-Version: 2.1
Name: yunbk
Version: 0.2.3
Summary: make backup easier
Author-email: dantezhu <zny2008@gmail.com>
License: MIT
Project-URL: Homepage, https://github.com/dantezhu/yunbk
Platform: any
License-File: LICENSE
Requires-Dist: paramiko
Requires-Dist: grandfatherson
